repology_mcp/__init__.py
repology_mcp/client.py
repology_mcp/models.py
repology_mcp/server.py
repology_mcp_server-0.1.1.dist-info/METADATA
repology_mcp_server-0.1.1.dist-info/WHEEL
repology_mcp_server-0.1.1.dist-info/entry_points.txt
repology_mcp_server-0.1.1.dist-info/licenses/LICENSE
repology_mcp_server-0.1.1.dist-info/RECORD
